{"is_source_file": true, "format": "HTML", "description": "This is an HTML template file for a web application's frontend, primarily setting up the document structure, including meta tags, external font links, and a root div for rendering the app via JavaScript.", "external_files": ["%PUBLIC_URL%/favicon.ico", "%PUBLIC_URL%/logo192.png", "%PUBLIC_URL%/manifest.json"], "external_methods": [], "published": [], "classes": [], "methods": [], "calls": [], "search-terms": ["HTML template", "index.html", "public folder", "React app root", "meta tags", "external fonts", "favicon", "manifest"], "state": 2, "file_id": 1, "knowledge_revision": 20, "git_revision": "e51409181c57c2935d529dcf7b452610dc5a913c", "hash": "d2b40d02d5f7873d8a6713bad837edd4", "format-version": 4, "code-base-name": "todo_frontend", "filename": "todo_frontend/public/index.html", "revision_history": [{"20": "e51409181c57c2935d529dcf7b452610dc5a913c"}]}